vivosun_thermo/__init__.py
vivosun_thermo/__main__.py
vivosun_thermo/app.py
vivosun_thermo/client.py
vivosun_thermo/conversion.py
vivosun_thermo/format.py
vivosun_thermo/py.typed
vivosun_thermo/scanner.py
vivosun_thermo-1.0.0.dist-info/LICENSE
vivosun_thermo-1.0.0.dist-info/METADATA
vivosun_thermo-1.0.0.dist-info/WHEEL
vivosun_thermo-1.0.0.dist-info/entry_points.txt
vivosun_thermo-1.0.0.dist-info/top_level.txt
vivosun_thermo-1.0.0.dist-info/RECORD
