Metadata-Version: 2.1
Name: vivosun-thermo
Version: 1.0.0
Summary: Python library and CLI tool for interacting with Vivosun Thermo devices via Bluetooth
Author-email: Artem Butusov <art.sormy@gmail.com>
License: Copyright 2025 Artem Butusov <art.sormy@gmail.com>
Project-URL: Homepage, https://github.com/sormy/vivosun-thermo
Project-URL: Issues, https://github.com/sormy/vivosun-thermo/issues
Keywords: Vivosun,AeroLab,Hygrometer,Thermometer,Thermo,VS-THB1S
Classifier: License :: OSI Approved :: MIT License
Classifier: Programming Language :: Python
Classifier: Programming Language :: Python :: 3
Requires-Python: >=3.10
License-File: LICENSE
Requires-Dist: bleak~=0.22.3
